runfalconbuildtools/__init__.py
runfalconbuildtools/__main__.py
runfalconbuildtools/app_builder.py
runfalconbuildtools/artifacts.py
runfalconbuildtools/aws_client.py
runfalconbuildtools/base_builder.py
runfalconbuildtools/command_line_executor.py
runfalconbuildtools/config_files_helper.py
runfalconbuildtools/docker_base.py
runfalconbuildtools/docker_image_builder.py
runfalconbuildtools/docker_image_tagger.py
runfalconbuildtools/docker_options.py
runfalconbuildtools/docker_tagger.py
runfalconbuildtools/env_utils.py
runfalconbuildtools/environment_helper.py
runfalconbuildtools/file_utils.py
runfalconbuildtools/keys_helper.py
runfalconbuildtools/logger.py
runfalconbuildtools/main_module.py
runfalconbuildtools/nodejs_typescript_builder.py
runfalconbuildtools/properties.py
runfalconbuildtools/repository_helper.py
runfalconbuildtools/ssl_certificate_manager.py
runfalconbuildtools/string_util.py
runfalcon_build_tools-1.4.1.dist-info/LICENCE
runfalcon_build_tools-1.4.1.dist-info/METADATA
runfalcon_build_tools-1.4.1.dist-info/WHEEL
runfalcon_build_tools-1.4.1.dist-info/top_level.txt
runfalcon_build_tools-1.4.1.dist-info/RECORD
