Metadata-Version: 2.1
Name: runfalcon-build-tools
Version: 1.4.1
Summary: Runfalcon tools to build process with quality and efficiency
Home-page: https://git-codecommit.zone.amazonaws.com/v1/repos/runfalcon-build-tools-py-package
Author: Raul A. de Villa C.
Author-email: r@runfalcon.com
Project-URL: Bug Tracker, https://no-yet
Classifier: Programming Language :: Python :: 3
Classifier: Operating System :: OS Independent
Requires-Python: >=3.6
License-File: LICENCE
